[
 {
  "i": 7289,
  "ep": "",
  "text": "请问",
  "prev": "雷：我不求别的，我走在街上，有人把我认出来，跟我要个签名什么的，我就知足了",
  "next": "郭芙蓉：打烊了，打烊了"
 },
 {
  "i": 7291,
  "ep": "",
  "text": "哎呀，不是吃饭，俺就想问你们这旮旯有个姓雷的吧",
  "prev": "郭芙蓉：打烊了，打烊了",
  "next": "雷：啊？"
 },
 {
  "i": 7294,
  "ep": "",
  "text": "我是个轿夫，左家庄的。这不，俺听说这雷老爷啊，通下水道可是一绝啊，专程来请他来了吗。",
  "prev": "白展堂：你找他干什么？",
  "next": "白展堂：你看我干啥呀，人又不找我。就这个，头破血流的这个雷老爷。"
 },
 {
  "i": 7296,
  "ep": "",
  "text": "哎呀妈呀，眼泪哗哗的，雷老爷啊，您方便吧，方便就跟俺去一趟呗",
  "prev": "白展堂：你看我干啥呀，人又不找我。就这个，头破血流的这个雷老爷。",
  "next": "雷：现在啊"
 },
 {
  "i": 7298,
  "ep": "",
  "text": "嗯呐。您不太方便吧，没关系，外头八抬大轿在正门口等您呢，我跟您说雷老爷，俺们村，锣鼓队，鞭炮队，还有开工酒，俺们庄的那老百姓张灯结彩都等着您呐，哎呀，您就去一回吧。",
  "prev": "雷：现在啊",
  "next": "雷：那，那我就"
 },
 {
  "i": 7305,
  "ep": "",
  "text": "哎",
  "prev": "雷：门口候着去",
  "next": "雷：各位，告辞了"
 },
 {
  "i": 7314,
  "ep": "",
  "text": "哎，我来我来，这事哪能劳烦雷老爷您呢，是不是",
  "prev": "雷：啥也不说了",
  "next": "雷：告辞！"
 },
 {
  "i": 7316,
  "ep": "",
  "text": "哎呀，雷老爷来了",
  "prev": "雷：告辞！",
  "next": "白展堂：终于逃过一劫呀"
 }
]