[
 {
  "i": 30139,
  "ep": "第60回",
  "text": "：是是是，再好的人参，它也有过劲儿的时候啊。",
  "prev": "郭芙蓉：呃，你是这个意思吧？",
  "next": "白展堂：可那万一要是人参精呢？你忘了？咱那人参已经长成人形了！"
 },
 {
  "i": 30141,
  "ep": "第60回",
  "text": "哎呀，不怕不怕，只要有耐心，总有云开雾散那一天！",
  "prev": "白展堂：可那万一要是人参精呢？你忘了？咱那人参已经长成人形了！",
  "next": "郭芙蓉：哎，那三五天之内有没有希望嘛！"
 },
 {
  "i": 30355,
  "ep": "第60回",
  "text": "别别别，有什么话您就直说吧。",
  "prev": "佟湘玉：可以，散了吧。南宫师妹请留步。来来来，坐坐坐，喝点茶吧。",
  "next": "佟湘玉：今天你一天都不在，你去哪了呀？"
 },
 {
  "i": 30357,
  "ep": "第60回",
  "text": "我出去转了转，这个镇还真很不错。依山傍水，风景秀丽，街道很干净，民风也很淳朴。",
  "prev": "佟湘玉：今天你一天都不在，你去哪了呀？",
  "next": "佟湘玉：哼哼，不够，远远不够，我理想中的七侠镇应该是一个世外桃源，路不拾遗，夜不闭户是最起码的。"
 },
 {
  "i": 30359,
  "ep": "第60回",
  "text": "这应该是知县操心的事吧？",
  "prev": "佟湘玉：哼哼，不够，远远不够，我理想中的七侠镇应该是一个世外桃源，路不拾遗，夜不闭户是最起码的。",
  "next": "佟湘玉：你错，国家兴亡，匹夫有责。"
 },
 {
  "i": 30361,
  "ep": "第60回",
  "text": "好好……",
  "prev": "佟湘玉：你错，国家兴亡，匹夫有责。",
  "next": "佟湘玉：今天的情况你也都看到了，之所以会这样，归根结底就是我们的工作没有做好……"
 },
 {
  "i": 30363,
  "ep": "第60回",
  "text": "对对对……",
  "prev": "佟湘玉：今天的情况你也都看到了，之所以会这样，归根结底就是我们的工作没有做好……",
  "next": "佟湘玉：所以我想请你给我们大家，做一个小型的报告会。"
 },
 {
  "i": 30365,
  "ep": "第60回",
  "text": "好好……什么会？",
  "prev": "佟湘玉：所以我想请你给我们大家，做一个小型的报告会。",
  "next": "佟湘玉：甭管什么会，反正你说好好好都答应了。不过你不要怕，所谓报告会呢，就是把大家找来，面对面的聊一聊，然后把你那个动物保护和主张素食给大家好好的宣传一下。"
 },
 {
  "i": 30367,
  "ep": "第60回",
  "text": "哎，别别别，这合适吗？我脸皮薄，你还是换个人吧。",
  "prev": "佟湘玉：甭管什么会，反正你说好好好都答应了。不过你不要怕，所谓报告会呢，就是把大家找来，面对面的聊一聊，然后把你那个动物保护和主张素食给大家好好的宣传一下。",
  "next": "佟湘玉：坐下，坐下，你不要忘了这可是你自己提出来的，你有思想有主张，谁能比你更有说服力呀？不要再推了，闲着也是闲着，还是帮我做点事情啊，你不要忘了，你给我们带来了多大的麻烦哪？这可是你将功赎罪的好机会呀。"
 },
 {
  "i": 30370,
  "ep": "第60回",
  "text": "这么多人？不成不成，那么多人，开什么玩笑啊，我见那么多人紧张，我真的不能演讲，我丢不起那脸。",
  "prev": "中场休息：洗衣记。郭、祝二美洗衣，秀才至，将衣托无双，小郭怒，自洗之，与无双眉来眼去，小郭亦怒，二美逛街，留秀才独洗。",
  "next": "佟湘玉：哎？啥叫丢脸？你这是造福于大家同时教育你自己，这份工作光荣得一塌糊涂。"
 },
 {
  "i": 30372,
  "ep": "第60回",
  "text": "哎呀，师姐，我求求你放过我吧，行吗？",
  "prev": "佟湘玉：哎？啥叫丢脸？你这是造福于大家同时教育你自己，这份工作光荣得一塌糊涂。",
  "next": "佟湘玉：我当初也是这么求你的，你放过我了吗？"
 },
 {
  "i": 30374,
  "ep": "第60回",
  "text": "我……哎呀，我真的不擅长演讲！人越多我越紧张，我连话都说不出来。",
  "prev": "佟湘玉：我当初也是这么求你的，你放过我了吗？",
  "next": "佟湘玉：哎呀哎呀，你不要唉声叹气的，演讲稿我已经帮你准备好了，你先顺一遍，来来来。"
 },
 {
  "i": 30376,
  "ep": "第60回",
  "text": "这跟动物保护有关系吗？",
  "prev": "佟湘玉：哎呀哎呀，你不要唉声叹气的，演讲稿我已经帮你准备好了，你先顺一遍，来来来。",
  "next": "佟湘玉：你不懂，先要励志，把气氛煽动起来，再将你那个动物保护，事半功倍。"
 },
 {
  "i": 30380,
  "ep": "第60回",
  "text": "照着念就行了？",
  "prev": "佟湘玉：就来！怎么样，准备好了吗？",
  "next": "佟湘玉：不是念，是散播，散播真情散播爱，用你的热情去感染他们，用你的诚恳去打动他们，去吧去吧，大家等着你呢。"
 },
 {
  "i": 30382,
  "ep": "第60回",
  "text": "看时光飞驰我，回首从前曾，经是莽撞，少年曾经度，日如年……",
  "prev": "佟湘玉：不是念，是散播，散播真情散播爱，用你的热情去感染他们，用你的诚恳去打动他们，去吧去吧，大家等着你呢。",
  "next": "龙套：好！"
 },
 {
  "i": 30384,
  "ep": "第60回",
  "text": "我是如此，平凡却，又如此幸，运我要说，声谢谢你……",
  "prev": "龙套：好！",
  "next": "龙套：说得好，比唱得还好听，可以上果盘了吗？"
 },
 {
  "i": 30386,
  "ep": "第60回",
  "text": "果盘？",
  "prev": "龙套：说得好，比唱得还好听，可以上果盘了吗？",
  "next": "龙套：你不是说听完报告一人发一果盘吗？"
 },
 {
  "i": 30388,
  "ep": "第60回",
  "text": "谁说的？",
  "prev": "龙套：你不是说听完报告一人发一果盘吗？",
  "next": "佟湘玉：我！没有事，你接着讲啊。不要着急，听完就上啊。"
 },
 {
  "i": 30390,
  "ep": "第60回",
  "text": "把握生命里，的每一分钟，全力以，赴我们心中，的梦……",
  "prev": "佟湘玉：我！没有事，你接着讲啊。不要着急，听完就上啊。",
  "next": "龙套：我们的梦就是果盘，再不上我们可撤了啊。还剩多少，你干脆一口气念完得了。"
 },
 {
  "i": 30392,
  "ep": "第60回",
  "text": "还剩……七八五十六页。",
  "prev": "龙套：我们的梦就是果盘，再不上我们可撤了啊。还剩多少，你干脆一口气念完得了。",
  "next": "龙套：不听了，不听了，为了果盘还不够累的呢，走走走。"
 },
 {
  "i": 30396,
  "ep": "第60回",
  "text": "我就说这不是我的强项嘛。",
  "prev": "佟湘玉：我跟你说了，让你不要念，你你的真心去散播真情，这叫散播吗？多好的演讲稿，我对你太失望了，白白给我浪费了。",
  "next": "佟湘玉：哟，那你的强项是什么呀？我觉得有句话说得特别好，叫天生我才必有用，一个人活在世上总有他的价值，但是你好象是个例外。"
 },
 {
  "i": 30398,
  "ep": "第60回",
  "text": "你这话什么意思啊？",
  "prev": "佟湘玉：哟，那你的强项是什么呀？我觉得有句话说得特别好，叫天生我才必有用，一个人活在世上总有他的价值，但是你好象是个例外。",
  "next": "佟湘玉：什么意思？你自己琢磨去吧，给你找来了这么多的人，要知道我自己上了。"
 },
 {
  "i": 30401,
  "ep": "第60回",
  "text": "师姐说，天生我才必有用，而我是个特例……",
  "prev": "白展堂：南宫，南宫？你怎么哭了？",
  "next": "李大嘴：她为啥这么说你呀？"
 },
 {
  "i": 30403,
  "ep": "第60回",
  "text": "她让我做真情报告会，那又不是我的强项，客人都是冲着果盘来的，走了也不能怨我呀……",
  "prev": "李大嘴：她为啥这么说你呀？",
  "next": "白展堂：不怨你，事到如今，咱们再也不能这么纵容她了，走！"
 },
 {
  "i": 30405,
  "ep": "第60回",
  "text": "别去，师姐好不容易苏醒过来，还没有完全恢复好呢，她也是没有办法，再说她又补了千年人参，把元气都补乱了，所以情绪激动也是正常的。",
  "prev": "白展堂：不怨你，事到如今，咱们再也不能这么纵容她了，走！",
  "next": "李大嘴：再怎么激动也不能这么折腾我们吧？啊，你说我都成啥了，我都成入室劫匪了我。"
 },
 {
  "i": 30436,
  "ep": "第60回",
  "text": "师姐，这是正常的，人参把你的元气都激发出来了，现在也耗费得差不多了。",
  "prev": "佟湘玉：不追了，谁爱追谁追去吧，我浑身发软，一点力气都没有。",
  "next": "李大嘴：没事，我屋里还有小半根呢。"
 },
 {
  "i": 30444,
  "ep": "第60回",
  "text": "师姐，休息啊。",
  "prev": "郭芙蓉：行了，行了，咱们也先撤吧，让掌柜的跟老白单独呆会。",
  "next": "白展堂：湘玉啊，你是不知道啊，这两天都要把我给烦死了。"
 },
 {
  "i": 30460,
  "ep": "第60回",
  "text": "师姐，你多保重，我先走了啊……",
  "prev": "佟湘玉：不为什么，我就是喜欢这种充满活力的感觉，这就是激情，这就是热血，这就是青春。青春啊青春，美丽的青春……",
  "next": "佟湘玉：站住，你不能走，你要是走了的话，那些可怜的动物怎么办？"
 },
 {
  "i": 30462,
  "ep": "第60回",
  "text": "让它们自生自灭吧……",
  "prev": "佟湘玉：站住，你不能走，你要是走了的话，那些可怜的动物怎么办？",
  "next": "佟湘玉：你怎么能说这样的话？你太让我失望了！"
 },
 {
  "i": 30464,
  "ep": "第60回",
  "text": "对不起啊，师姐，这几天发生这么多事情，我脑子已经蒙了，看在同门的情谊上，你就让我做一个堂堂正正的废物吧，再见！",
  "prev": "佟湘玉：你怎么能说这样的话？你太让我失望了！",
  "next": "佟湘玉：巧了，我的强项就是变废物为宝物，过来，帮我顺一下讲演稿……"
 },
 {
  "i": 30466,
  "ep": "第60回",
  "text": "诸位保重，后会有期啊！",
  "prev": "佟湘玉：巧了，我的强项就是变废物为宝物，过来，帮我顺一下讲演稿……",
  "next": "佟湘玉：展堂……"
 },
 {
  "i": 30468,
  "ep": "第60回",
  "text": "再见了，再见了……",
  "prev": "佟湘玉：展堂……",
  "next": "白展堂：你走了，你要求的我们怎么做到？"
 },
 {
  "i": 30470,
  "ep": "第60回",
  "text": "只能靠大家自觉了。",
  "prev": "白展堂：你走了，你要求的我们怎么做到？",
  "next": "白展堂：南宫，你这几天讲的都很有道理，但是我觉得，凡事都要有一个度。"
 },
 {
  "i": 30472,
  "ep": "第60回",
  "text": "对不起，我好象没听懂，",
  "prev": "白展堂：南宫，你这几天讲的都很有道理，但是我觉得，凡事都要有一个度。",
  "next": "白展堂：你这边请，崇尚自然，天人合一，这都没有错，但是你忘了一点，人类本身就是食物链中的一环，如果光吃素，这个食物链不就断了吗，那对自然有什么益处吗？"
 },
 {
  "i": 30474,
  "ep": "第60回",
  "text": "这……",
  "prev": "白展堂：你这边请，崇尚自然，天人合一，这都没有错，但是你忘了一点，人类本身就是食物链中的一环，如果光吃素，这个食物链不就断了吗，那对自然有什么益处吗？",
  "next": "白展堂：我们驯服了野牛野马，饲养家禽家畜，这样既保证了食物链的完整，又没有破坏自然环境，从这一点上来讲，我们没有错，当然，滥捕滥杀另当别论。"
 },
 {
  "i": 30476,
  "ep": "第60回",
  "text": "你说得很对，那我下一步的主张，就是反对滥捕滥杀。",
  "prev": "白展堂：我们驯服了野牛野马，饲养家禽家畜，这样既保证了食物链的完整，又没有破坏自然环境，从这一点上来讲，我们没有错，当然，滥捕滥杀另当别论。",
  "next": "白展堂：这就对了，"
 },
 {
  "i": 30478,
  "ep": "第60回",
  "text": "这段时间，我给大家添了许多麻烦，替我给大家赔个不是，日后有缘相见吧。",
  "prev": "白展堂：这就对了，",
  "next": "白展堂：再会。"
 },
 {
  "i": 30480,
  "ep": "第60回",
  "text": "再会。",
  "prev": "白展堂：再会。",
  "next": "白展堂：你去哪？"
 },
 {
  "i": 30482,
  "ep": "第60回",
  "text": "我去可可西里，听说那里有许多藏羚羊。",
  "prev": "白展堂：你去哪？",
  "next": "白展堂：我看好你哟。"
 }
]